slack_dlp_sdk/__init__.py
slack_dlp_sdk/cli/__init__.py
slack_dlp_sdk/cli/cli_client.py
slack_dlp_sdk/cli/commands/alerts.py
slack_dlp_sdk/cli/commands/rules.py
slack_dlp_sdk/client.py
slack_dlp_sdk/constants.py
slack_dlp_sdk/exceptions.py
slack_dlp_sdk/sdk/__init__.py
slack_dlp_sdk/sdk/alerts.py
slack_dlp_sdk/sdk/http.py
slack_dlp_sdk/sdk/models.py
slack_dlp_sdk/sdk/rules.py
slack_dlp_sdk/sdk/types.py
slack_dlp_sdk-0.1.0.dist-info/METADATA
slack_dlp_sdk-0.1.0.dist-info/WHEEL
slack_dlp_sdk-0.1.0.dist-info/entry_points.txt
slack_dlp_sdk-0.1.0.dist-info/licenses/LICENSE
slack_dlp_sdk-0.1.0.dist-info/RECORD
