Metadata-Version: 2.4
Name: slack-dlp-sdk
Version: 0.1.0
Summary: A Python SDK for interacting with Slack Data Loss Prevention (DLP)
License-File: LICENSE
Author: PaperMtn
Author-email: me@papermtn.co.uk
Requires-Python: >=3.11
Classifier: Programming Language :: Python :: 3
Classifier: Programming Language :: Python :: 3.11
Classifier: Programming Language :: Python :: 3.12
Classifier: Programming Language :: Python :: 3.13
Classifier: Programming Language :: Python :: 3.14
Requires-Dist: requests (>=2.32.5,<3.0.0)
